{
  "tags#87": "",
  "tags#86": "",
  "tags#89": "",
  "tags#88": "",
  "tags#81": "",
  "tags#80": "",
  "tags#83": "",
  "tags#82": "",
  "tags#85": "",
  "tags#84": "",
  "tags#76": "",
  "tags#75": "",
  "tags#78": "",
  "tags#77": "",
  "tags#79": "",
  "tags#70": "",
  "tags#72": "",
  "tags#71": "",
  "tags#74": "",
  "tags#73": "",
  "category#24": "Cocina",
  "category#23": "Cocina",
  "category#22": "Dormitorio",
  "category#21": "Salón",
  "category#20": "Puertas y Ventanas",
  "category#29": "Cocina",
  "category#28": "Cocina",
  "category#27": "Escaleras",
  "category#26": "Salón",
  "category#25": "Dormitorio",
  "category#13": "Puertas y Ventanas",
  "category#12": "Puertas y Ventanas",
  "category#11": "Salón",
  "category#10": "Dormitorio",
  "name#100": "Horno",
  "category#19": "Puertas y Ventanas",
  "category#18": "Puertas y Ventanas",
  "category#17": "Puertas y Ventanas",
  "category#16": "Puertas y Ventanas",
  "category#15": "Puertas y Ventanas",
  "category#14": "Puertas y Ventanas",
  "tags#98": "",
  "tags#97": "",
  "tags#99": "",
  "tags#90": "",
  "tags#92": "",
  "tags#91": "",
  "tags#94": "",
  "tags#93": "",
  "tags#96": "",
  "tags#95": "",
  "tags#43": "",
  "tags#42": "",
  "tags#45": "",
  "tags#44": "",
  "tags#47": "",
  "tags#46": "",
  "tags#49": "",
  "tags#48": "",
  "tags#41": "",
  "tags#40": "",
  "category#4": "Salón",
  "category#3": "Dormitorio",
  "tags#39": "",
  "category#2": "Dormitorio",
  "category#1": "Dormitorio",
  "name#90": "Estantería",
  "tags#32": "",
  "name#93": "Barandilla",
  "tags#31": "",
  "name#94": "Campana",
  "tags#34": "",
  "name#91": "Acuario",
  "category#9": "Cuarto de Baño",
  "tags#33": "",
  "name#92": "Ventana con apertura hacia afuera",
  "category#8": "Cuarto de Baño",
  "tags#36": "",
  "name#97": "Silla",
  "category#7": "Cuarto de Baño",
  "tags#35": "",
  "name#98": "Persiana Veneciana",
  "category#6": "Salón",
  "tags#38": "",
  "name#95": "Mesa de café",
  "category#5": "Salón",
  "tags#37": "",
  "name#96": "Mesa rectangular",
  "name#99": "Barra cortina",
  "tags#30": "",
  "tags#65": "",
  "tags#64": "",
  "tags#67": "",
  "tags#66": "",
  "tags#69": "",
  "tags#68": "",
  "tags#61": "",
  "tags#60": "",
  "tags#63": "",
  "tags#62": "",
  "tags#54": "",
  "tags#53": "",
  "tags#56": "",
  "tags#55": "",
  "tags#58": "",
  "tags#57": "",
  "tags#59": "",
  "tags#50": "",
  "tags#52": "",
  "tags#51": "",
  "name#7": "Inodoro",
  "name#6": "Mesa redonda",
  "category#89": "Salón",
  "name#5": "Silla",
  "category#88": "Iluminación",
  "name#4": "Estantería",
  "category#87": "Varios",
  "name#3": "Mesita",
  "category#86": "Salón",
  "name#2": "Cómoda",
  "category#85": "Salón",
  "name#1": "Cama 140x190",
  "category#84": "Salón",
  "category#83": "Puertas y Ventanas",
  "name#61": "Lámpara de pie",
  "name#60": "Bombilla magenta",
  "name#63": "Lámpara de techo",
  "name#62": "Lámpara de foco",
  "name#65": "Aplique de pared",
  "name#64": "Flexo",
  "name#67": "Ventana triangular",
  "category#93": "Varios",
  "name#66": "Marco de ouerta con arco semicircular",
  "category#92": "Puertas y Ventanas",
  "name#69": "Ventana circular",
  "category#91": "Salón",
  "name#68": "Ventana semicircular",
  "category#90": "Salón",
  "category#79": "Dormitorio",
  "category#78": "Salón",
  "category#77": "Escaleras",
  "category#76": "Varios",
  "category#75": "Cocina",
  "category#74": "Puertas y Ventanas",
  "category#73": "Salón",
  "category#72": "Salón",
  "tags#3": "",
  "tags#2": "",
  "tags#5": "",
  "name#50": "Radiador agua caliente",
  "tags#4": "",
  "tags#7": "",
  "name#52": "Ventana fija",
  "tags#6": "",
  "name#51": "Agujero en la pared",
  "tags#9": "",
  "name#54": "Bombilla halógena",
  "tags#8": "",
  "name#53": "Bombilla blanca",
  "name#56": "Bombilla fucsia",
  "category#82": "Varios",
  "name#55": "Bombilla incandescente",
  "category#81": "Salón",
  "name#58": "Bombilla verde",
  "category#80": "Salón",
  "name#57": "Bombilla roja",
  "name#59": "Bombilla azul",
  "tags#1": "",
  "tags#29": "",
  "tags#28": "",
  "tags#21": "",
  "name#81": "Vitrina",
  "tags#20": "",
  "name#80": "Chimenea",
  "tags#23": "",
  "name#83": "Puerta de garaje",
  "tags#22": "",
  "name#82": "Cuadro",
  "tags#25": "",
  "name#85": "Sofá",
  "tags#24": "",
  "name#84": "Butaca",
  "tags#27": "",
  "name#87": "Maniquí",
  "tags#26": "",
  "name#86": "Escritorio",
  "name#89": "Aparador",
  "name#88": "Lámpara",
  "category#99": "Varios",
  "category#98": "Varios",
  "category#97": "Salón",
  "category#96": "Salón",
  "category#95": "Salón",
  "category#94": "Cocina",
  "tags#18": "",
  "tags#17": "",
  "tags#19": "",
  "tags#10": "",
  "name#70": "Puerta con arco semicircular",
  "tags#12": "",
  "name#72": "TV Plana",
  "tags#11": "",
  "name#71": "Cama",
  "tags#14": "",
  "name#74": "Puerta de Entrada",
  "tags#13": "",
  "name#73": "Flores",
  "tags#16": "",
  "name#76": "Triángulo",
  "tags#15": "",
  "name#75": "Armario superior",
  "name#78": "Portatil",
  "name#77": "Escalera de caracol",
  "name#79": "Cuna",
  "name#9": "Bañera con patas",
  "name#8": "Lavabo",
  "category#46": "Cuarto de Baño",
  "name#19": "Puerta",
  "category#45": "Cuarto de Baño",
  "category#44": "Varios",
  "category#43": "Puertas y Ventanas",
  "category#42": "Puertas y Ventanas",
  "category#41": "Varios",
  "category#40": "Dormitorio",
  "category#49": "Varios",
  "category#48": "Cuarto de Baño",
  "category#47": "Dormitorio",
  "name#21": "Sillón",
  "name#20": "Puerta abierta",
  "name#23": "Lavadora",
  "name#22": "Litera",
  "name#25": "Litera en esquina",
  "name#24": "Cocina",
  "name#27": "Escalera en curva",
  "name#26": "Chaise longue",
  "name#29": "Frigorífico",
  "name#28": "Lavavajillas",
  "category#35": "Salón",
  "category#34": "Cocina",
  "category#33": "Salón",
  "category#32": "Dormitorio",
  "category#31": "Cocina",
  "category#30": "Cocina",
  "category#39": "Salón",
  "category#38": "Salón",
  "category#37": "Escaleras",
  "category#36": "Salón",
  "name#10": "Cama 90x190",
  "name#12": "Ventana pequeña",
  "name#11": "Planta",
  "name#14": "Ventana Francesa",
  "name#13": "Ventana",
  "name#16": "Ventana doble",
  "category#100": "Cocina",
  "name#15": "Ventana doble pequeña",
  "name#18": "Ventana de guillotina",
  "name#17": "Ventana doble Francesa",
  "category#68": "Puertas y Ventanas",
  "category#67": "Puertas y Ventanas",
  "category#66": "Puertas y Ventanas",
  "category#65": "Iluminación",
  "category#64": "Iluminación",
  "category#63": "Iluminación",
  "category#62": "Iluminación",
  "category#61": "Iluminación",
  "category#69": "Puertas y Ventanas",
  "name#41": "Caja",
  "name#40": "Armario",
  "name#43": "Ventana corredera",
  "name#42": "Marco puerta",
  "name#45": "Bañera",
  "category#71": "Dormitorio",
  "name#44": "Cylindro",
  "category#70": "Puertas y Ventanas",
  "name#47": "Puertas correderas",
  "name#46": "Armario lavabo",
  "name#49": "Radiador electrico",
  "name#48": "Plato de ducha",
  "category#57": "Iluminación",
  "category#56": "Iluminación",
  "category#55": "Iluminación",
  "category#54": "Iluminación",
  "category#53": "Iluminación",
  "category#52": "Puertas y Ventanas",
  "category#51": "Puertas y Ventanas",
  "category#50": "Varios",
  "tags#100": "",
  "category#59": "Iluminación",
  "category#58": "Iluminación",
  "name#30": "Combi",
  "name#32": "Cama elevada 140x190",
  "name#31": "Mueble cocina",
  "name#34": "Fregadero",
  "category#60": "Iluminación",
  "name#33": "Piano",
  "name#36": "Mesa cuadrada",
  "name#35": "Sofá",
  "name#38": "Taburete",
  "name#37": "Escalera",
  "name#39": "Mesa TV"
}
